<?xml-stylesheet type="text/xsl" href="../../xslt/element.xslt"?>
<element number="dCustomResults.02"  minOccurs="1"  maxOccurs="1"  dataTypeName="CorrelationID"  isNillable="No">
<name>Custom Element ID Referenced</name>
<national>No</national>
<deprecated></deprecated>
<state>No</state>
<definition>References the CustomElementID attribute for dCustomConfiguration.CustomGroup</definition>
<v2Number></v2Number>
<usage>Mandatory</usage>
<performanceMeasuresGroup></performanceMeasuresGroup>
<v3Comment></v3Comment>
<v3Changes></v3Changes>
<deprecatedComment></deprecatedComment>
<restrictions>
  <CorrelationID baseType="string">
    <facet name="minLength" value="0"/>
    <facet name="maxLength" value="255"/>
  </CorrelationID>
</restrictions>
</element>
