<MedDeviceDataSet xmlns:xsi="http://www.w3.org/2001/XMLSchema-instance" xsi:schemaLocation="http://www.nemsis.org file:///C:/Sandbox/NemsisXSDs/XSDv3.2.5/MedDeviceDataSet_v3.xsd"  xmlns="http://www.nemsis.org">
    <eCustomConfiguration>
        <eCustomConfiguration.CustomGroup CustomElementID="">
            <eCustomConfiguration.01>KD</eCustomConfiguration.01>
            <eCustomConfiguration.02></eCustomConfiguration.02>
            <eCustomConfiguration.03>9902007</eCustomConfiguration.03>
            <eCustomConfiguration.04>9923003</eCustomConfiguration.04>
            <eCustomConfiguration.05>9903001</eCustomConfiguration.05>
            <eCustomConfiguration.06>8</eCustomConfiguration.06>
            <eCustomConfiguration.06>a</eCustomConfiguration.06>
            <eCustomConfiguration.07>7701001</eCustomConfiguration.07>
            <eCustomConfiguration.07>7701003</eCustomConfiguration.07>
            <eCustomConfiguration.07>7701005</eCustomConfiguration.07>
            
            <eCustomConfiguration.08>8801021</eCustomConfiguration.08>
            <eCustomConfiguration.08>8801009</eCustomConfiguration.08>
            <eCustomConfiguration.08>8801003</eCustomConfiguration.08>
            <eCustomConfiguration.08>8801013</eCustomConfiguration.08>
        </eCustomConfiguration.CustomGroup>
        <eCustomConfiguration.CustomGroup CustomElementID="">
            <eCustomConfiguration.01>2o</eCustomConfiguration.01>
            <eCustomConfiguration.02></eCustomConfiguration.02>
            <eCustomConfiguration.03>9902007</eCustomConfiguration.03>
            <eCustomConfiguration.04>9923003</eCustomConfiguration.04>
            <eCustomConfiguration.05>9903001</eCustomConfiguration.05>
            <eCustomConfiguration.06>2</eCustomConfiguration.06>
            <eCustomConfiguration.06>F</eCustomConfiguration.06>
            <eCustomConfiguration.06>y</eCustomConfiguration.06>
            <eCustomConfiguration.06>s</eCustomConfiguration.06>
            <eCustomConfiguration.07>7701001</eCustomConfiguration.07>
            <eCustomConfiguration.07>7701003</eCustomConfiguration.07>
            <eCustomConfiguration.07>7701005</eCustomConfiguration.07>
            
            <eCustomConfiguration.08>8801021</eCustomConfiguration.08>
            <eCustomConfiguration.08>8801009</eCustomConfiguration.08>
            <eCustomConfiguration.08>8801003</eCustomConfiguration.08>
        </eCustomConfiguration.CustomGroup>
        <eCustomConfiguration.CustomGroup CustomElementID="">
            <eCustomConfiguration.01>DT</eCustomConfiguration.01>
            <eCustomConfiguration.02></eCustomConfiguration.02>
            <eCustomConfiguration.03>9902007</eCustomConfiguration.03>
            <eCustomConfiguration.04>9923003</eCustomConfiguration.04>
            <eCustomConfiguration.05>9903001</eCustomConfiguration.05>
            <eCustomConfiguration.06>u</eCustomConfiguration.06>
            <eCustomConfiguration.06>A</eCustomConfiguration.06>
            <eCustomConfiguration.06>1</eCustomConfiguration.06>
            <eCustomConfiguration.06>S</eCustomConfiguration.06>
            <eCustomConfiguration.07>7701001</eCustomConfiguration.07>
            <eCustomConfiguration.07>7701003</eCustomConfiguration.07>
            <eCustomConfiguration.07>7701005</eCustomConfiguration.07>
            <eCustomConfiguration.08>8801021</eCustomConfiguration.08>
            <eCustomConfiguration.08>8801009</eCustomConfiguration.08>
            <eCustomConfiguration.08>8801003</eCustomConfiguration.08>
            <eCustomConfiguration.08>8801013</eCustomConfiguration.08>
            <eCustomConfiguration.08>8801001</eCustomConfiguration.08>
        </eCustomConfiguration.CustomGroup>
        <eCustomConfiguration.CustomGroup CustomElementID="">
            <eCustomConfiguration.01>f3</eCustomConfiguration.01>
            <eCustomConfiguration.02></eCustomConfiguration.02>
            <eCustomConfiguration.03>9902007</eCustomConfiguration.03>
            <eCustomConfiguration.04>9923003</eCustomConfiguration.04>
            <eCustomConfiguration.05>9903001</eCustomConfiguration.05>
            <eCustomConfiguration.06>6</eCustomConfiguration.06>
            <eCustomConfiguration.06>7</eCustomConfiguration.06>
            <eCustomConfiguration.07>7701001</eCustomConfiguration.07>
            <eCustomConfiguration.07>7701003</eCustomConfiguration.07>
            <eCustomConfiguration.07>7701005</eCustomConfiguration.07>
            
            <eCustomConfiguration.08>8801021</eCustomConfiguration.08>
            <eCustomConfiguration.08>8801009</eCustomConfiguration.08>
            <eCustomConfiguration.08>8801003</eCustomConfiguration.08>
            <eCustomConfiguration.08>8801013</eCustomConfiguration.08>
        </eCustomConfiguration.CustomGroup>
        <eCustomConfiguration.CustomGroup CustomElementID="">
            <eCustomConfiguration.01>XX</eCustomConfiguration.01>
            <eCustomConfiguration.02></eCustomConfiguration.02>
            <eCustomConfiguration.03>9902007</eCustomConfiguration.03>
            <eCustomConfiguration.04>9923003</eCustomConfiguration.04>
            <eCustomConfiguration.05>9903001</eCustomConfiguration.05>
            <eCustomConfiguration.06>K</eCustomConfiguration.06>
            <eCustomConfiguration.06>J</eCustomConfiguration.06>
            <eCustomConfiguration.06>D</eCustomConfiguration.06>
            <eCustomConfiguration.06>I</eCustomConfiguration.06>
            <eCustomConfiguration.06>p</eCustomConfiguration.06>
            <eCustomConfiguration.07>7701001</eCustomConfiguration.07>
            <eCustomConfiguration.07>7701003</eCustomConfiguration.07>
            <eCustomConfiguration.07>7701005</eCustomConfiguration.07>
            
            <eCustomConfiguration.08>8801021</eCustomConfiguration.08>
            <eCustomConfiguration.08>8801009</eCustomConfiguration.08>
            <eCustomConfiguration.08>8801003</eCustomConfiguration.08>
        </eCustomConfiguration.CustomGroup>
    </eCustomConfiguration>
    <eMedDevice>
        <eMedDevice.01>G</eMedDevice.01>
        <eMedDevice.02>1</eMedDevice.02>
        <eMedDevice.03>lX</eMedDevice.03>
        <eMedDevice.04>W3</eMedDevice.04>
        <eMedDevice.05>8o</eMedDevice.05>
        <eMedDevice.06>tY</eMedDevice.06>
        <eMedDevice.07>1603001</eMedDevice.07>
        <eMedDevice.07>1603031</eMedDevice.07>
        <eMedDevice.08>tW</eMedDevice.08>
        <eMedDevice.09>nL</eMedDevice.09>
        <eMedDevice.10>Rf4</eMedDevice.10>
        <eMedDevice.PatientNameGroup>
            <eMedDevice.11>7</eMedDevice.11>
            <eMedDevice.12>8</eMedDevice.12>
            <eMedDevice.13>F</eMedDevice.13>
            <eMedDevice.14>9906001</eMedDevice.14>
            <eMedDevice.15>2514007</eMedDevice.15>
            <eMedDevice.15>2514009</eMedDevice.15>
            <eMedDevice.15>2514003</eMedDevice.15>
            <eMedDevice.15>2514005</eMedDevice.15>
        </eMedDevice.PatientNameGroup>
        <eMedDevice.PatientAgeGroup>
            <eMedDevice.16>2</eMedDevice.16>
            <eMedDevice.17>2516009</eMedDevice.17>
        </eMedDevice.PatientAgeGroup>
        <eMedDevice.18>1957-05-07</eMedDevice.18>
        <eMedDevice.VitalsGroup>
            <eMedDevice.19>2000-07-22T01:07:54+07:00</eMedDevice.19>
            <eMedDevice.CardiacRhythmGroup>
                <eMedDevice.20>9901063</eMedDevice.20>
                <eMedDevice.20>9901039</eMedDevice.20>
                <eMedDevice.20>9901013</eMedDevice.20>
                <eMedDevice.21>3304009</eMedDevice.21>
                <eMedDevice.22>3305003</eMedDevice.22>
                <eMedDevice.22>3305001</eMedDevice.22>
                <eMedDevice.22>3305007</eMedDevice.22>
            </eMedDevice.CardiacRhythmGroup>
            <eMedDevice.BloodPressureGroup>
                <eMedDevice.23>253</eMedDevice.23>
                <eMedDevice.24>51</eMedDevice.24>
                <eMedDevice.25>3308009</eMedDevice.25>
                <eMedDevice.26>6</eMedDevice.26>
            </eMedDevice.BloodPressureGroup>
            <eMedDevice.HeartRateGroup>
                <eMedDevice.27>387</eMedDevice.27>
                <eMedDevice.28>3311011</eMedDevice.28>
            </eMedDevice.HeartRateGroup>
            <eMedDevice.29>78</eMedDevice.29>
            <eMedDevice.30>33</eMedDevice.30>
            <eMedDevice.31>71</eMedDevice.31>
            <eMedDevice.32>8</eMedDevice.32>
            <eMedDevice.33>1804</eMedDevice.33>
            <eMedDevice.BodyTempuratureGroup>
                <eMedDevice.34>9.0</eMedDevice.34>
                <eMedDevice.35>3325003</eMedDevice.35>
            </eMedDevice.BodyTempuratureGroup>
        </eMedDevice.VitalsGroup>
        <eMedDevice.VitalsGroup>
            <eMedDevice.19>1997-08-25T03:51:42+07:00</eMedDevice.19>
            <eMedDevice.CardiacRhythmGroup>
                <eMedDevice.20>9901063</eMedDevice.20>
                <eMedDevice.20>9901039</eMedDevice.20>
                <eMedDevice.20>9901013</eMedDevice.20>
                <eMedDevice.21>3304009</eMedDevice.21>
                <eMedDevice.22>3305003</eMedDevice.22>
                <eMedDevice.22>3305001</eMedDevice.22>
                <eMedDevice.22>3305007</eMedDevice.22>
            </eMedDevice.CardiacRhythmGroup>
            <eMedDevice.BloodPressureGroup>
                <eMedDevice.23>131</eMedDevice.23>
                <eMedDevice.24>P</eMedDevice.24>
                <eMedDevice.25>3308009</eMedDevice.25>
                <eMedDevice.26>109</eMedDevice.26>
            </eMedDevice.BloodPressureGroup>
            <eMedDevice.HeartRateGroup>
                <eMedDevice.27>441</eMedDevice.27>
                <eMedDevice.28>3311011</eMedDevice.28>
            </eMedDevice.HeartRateGroup>
            <eMedDevice.29>67</eMedDevice.29>
            <eMedDevice.30>147</eMedDevice.30>
            <eMedDevice.31>16</eMedDevice.31>
            <eMedDevice.32>82</eMedDevice.32>
            <eMedDevice.33>1181</eMedDevice.33>
            <eMedDevice.BodyTempuratureGroup>
                <eMedDevice.34>18.0</eMedDevice.34>
                <eMedDevice.35>3325003</eMedDevice.35>
            </eMedDevice.BodyTempuratureGroup>
        </eMedDevice.VitalsGroup>
        <eMedDevice.VitalsGroup>
            <eMedDevice.19>1960-06-03T09:44:59+07:00</eMedDevice.19>
            <eMedDevice.CardiacRhythmGroup>
                <eMedDevice.20>9901063</eMedDevice.20>
                <eMedDevice.20>9901039</eMedDevice.20>
                <eMedDevice.20>9901013</eMedDevice.20>
                <eMedDevice.20>9901065</eMedDevice.20>
                <eMedDevice.21>3304009</eMedDevice.21>
                <eMedDevice.22>3305003</eMedDevice.22>
                <eMedDevice.22>3305001</eMedDevice.22>
            </eMedDevice.CardiacRhythmGroup>
            <eMedDevice.BloodPressureGroup>
                <eMedDevice.23>386</eMedDevice.23>
                <eMedDevice.24>0</eMedDevice.24>
                <eMedDevice.25>3308009</eMedDevice.25>
                <eMedDevice.26>340</eMedDevice.26>
            </eMedDevice.BloodPressureGroup>
            <eMedDevice.HeartRateGroup>
                <eMedDevice.27>360</eMedDevice.27>
                <eMedDevice.28>3311011</eMedDevice.28>
            </eMedDevice.HeartRateGroup>
            <eMedDevice.29>12</eMedDevice.29>
            <eMedDevice.30>31</eMedDevice.30>
            <eMedDevice.31>18</eMedDevice.31>
            <eMedDevice.32>0</eMedDevice.32>
            <eMedDevice.33>1429</eMedDevice.33>
            <eMedDevice.BodyTempuratureGroup>
                <eMedDevice.34>23.0</eMedDevice.34>
                <eMedDevice.35>3325003</eMedDevice.35>
            </eMedDevice.BodyTempuratureGroup>
        </eMedDevice.VitalsGroup>
        <eMedDevice.VitalsGroup>
            <eMedDevice.19>2002-11-23T06:47:09+07:00</eMedDevice.19>
            <eMedDevice.CardiacRhythmGroup>
                <eMedDevice.20>9901063</eMedDevice.20>
                <eMedDevice.20>9901039</eMedDevice.20>
                <eMedDevice.21>3304009</eMedDevice.21>
                <eMedDevice.22>3305003</eMedDevice.22>
                <eMedDevice.22>3305001</eMedDevice.22>
                <eMedDevice.22>3305007</eMedDevice.22>
                <eMedDevice.22>3305005</eMedDevice.22>
            </eMedDevice.CardiacRhythmGroup>
            <eMedDevice.BloodPressureGroup>
                <eMedDevice.23>9</eMedDevice.23>
                <eMedDevice.24>p</eMedDevice.24>
                <eMedDevice.25>3308009</eMedDevice.25>
                <eMedDevice.26>401</eMedDevice.26>
            </eMedDevice.BloodPressureGroup>
            <eMedDevice.HeartRateGroup>
                <eMedDevice.27>66</eMedDevice.27>
                <eMedDevice.28>3311011</eMedDevice.28>
            </eMedDevice.HeartRateGroup>
            <eMedDevice.29>95</eMedDevice.29>
            <eMedDevice.30>40</eMedDevice.30>
            <eMedDevice.31>93</eMedDevice.31>
            <eMedDevice.32>24</eMedDevice.32>
            <eMedDevice.33>1855</eMedDevice.33>
            <eMedDevice.BodyTempuratureGroup>
                <eMedDevice.34>24.0</eMedDevice.34>
                <eMedDevice.35>3325003</eMedDevice.35>
            </eMedDevice.BodyTempuratureGroup>
        </eMedDevice.VitalsGroup>
        <eMedDevice.VitalsGroup>
            <eMedDevice.19>1991-08-19T03:29:47+07:00</eMedDevice.19>
            <eMedDevice.CardiacRhythmGroup>
                <eMedDevice.20>9901063</eMedDevice.20>
                <eMedDevice.20>9901039</eMedDevice.20>
                <eMedDevice.21>3304009</eMedDevice.21>
                <eMedDevice.22>3305003</eMedDevice.22>
                <eMedDevice.22>3305001</eMedDevice.22>
                <eMedDevice.22>3305007</eMedDevice.22>
            </eMedDevice.CardiacRhythmGroup>
            <eMedDevice.BloodPressureGroup>
                <eMedDevice.23>241</eMedDevice.23>
                <eMedDevice.24>p</eMedDevice.24>
                <eMedDevice.25>3308009</eMedDevice.25>
                <eMedDevice.26>337</eMedDevice.26>
            </eMedDevice.BloodPressureGroup>
            <eMedDevice.HeartRateGroup>
                <eMedDevice.27>465</eMedDevice.27>
                <eMedDevice.28>3311011</eMedDevice.28>
            </eMedDevice.HeartRateGroup>
            <eMedDevice.29>34</eMedDevice.29>
            <eMedDevice.30>136</eMedDevice.30>
            <eMedDevice.31>62</eMedDevice.31>
            <eMedDevice.32>45</eMedDevice.32>
            <eMedDevice.33>449</eMedDevice.33>
            <eMedDevice.BodyTempuratureGroup>
                <eMedDevice.34>32.0</eMedDevice.34>
                <eMedDevice.35>3325003</eMedDevice.35>
            </eMedDevice.BodyTempuratureGroup>
        </eMedDevice.VitalsGroup>
        <eMedDevice.LabsGroup>
            <eMedDevice.36>1978-05-16T01:01:47+07:00</eMedDevice.36>
            <eMedDevice.LabResultGroup>
                <eMedDevice.37>3403045</eMedDevice.37>
                <eMedDevice.38>g</eMedDevice.38>
            </eMedDevice.LabResultGroup>
            <eMedDevice.LabResultGroup>
                <eMedDevice.37>3403045</eMedDevice.37>
                <eMedDevice.38>n</eMedDevice.38>
            </eMedDevice.LabResultGroup>
            <eMedDevice.LabImageGroup>
                <eMedDevice.39>3405001</eMedDevice.39>
                <eMedDevice.40>ueu</eMedDevice.40>
                <eMedDevice.WaveFormGraphicGroup>
                    <eMedDevice.41>Z</eMedDevice.41>
                    <eMedDevice.42>UElXUkdTOVUwVERUNUM2MzBEQzdjMmNCVk9Ra2JQNVpSbUF6VGhyY2RwUXM2dGp1bTE=</eMedDevice.42>
                </eMedDevice.WaveFormGraphicGroup>
                <eMedDevice.WaveFormGraphicGroup>
                    <eMedDevice.41>p</eMedDevice.41>
                    <eMedDevice.42>ZlhvQ3J6b3lWeHZRaHZXb3BOWlh1YlFzSEF6SXdOR29uYXpqTE4xRGlMWWFIbDdMd0E=</eMedDevice.42>
                </eMedDevice.WaveFormGraphicGroup>
                <eMedDevice.WaveFormGraphicGroup>
                    <eMedDevice.41>2</eMedDevice.41>
                    <eMedDevice.42>U1NMMzhacVkxbzhrNGRkVE9KaDJRcm9FVmJOck9IaGtaR1pYZWpETXN5Rll3bTFjVWw=</eMedDevice.42>
                </eMedDevice.WaveFormGraphicGroup>
                <eMedDevice.WaveFormGraphicGroup>
                    <eMedDevice.41>c</eMedDevice.41>
                    <eMedDevice.42>MnB2ellpc3JqWkpHV2d5M1l1OTJIWlhzemlhVTcyYjY2ajNrRnVUMW5ZS3pBeE9yNHg=</eMedDevice.42>
                </eMedDevice.WaveFormGraphicGroup>
                <eMedDevice.WaveFormGraphicGroup>
                    <eMedDevice.41>G</eMedDevice.41>
                    <eMedDevice.42>N1ZITlJOdUlwMFpiMXhBVFl1OFkwdVNSSGpvQml6RWI2UVhiSm5BSXlwWkpWa1lmVko=</eMedDevice.42>
                </eMedDevice.WaveFormGraphicGroup>
            </eMedDevice.LabImageGroup>
            <eMedDevice.LabImageGroup>
                <eMedDevice.39>3405001</eMedDevice.39>
                <eMedDevice.40>fDM</eMedDevice.40>
                <eMedDevice.WaveFormGraphicGroup>
                    <eMedDevice.41>m</eMedDevice.41>
                    <eMedDevice.42>UUhLd0R5dXI0Um9RRnVJNGExbFVVem1BYkJGUzhwY1FPSzBvM2tRU3JEVnJTSEVuYmU=</eMedDevice.42>
                </eMedDevice.WaveFormGraphicGroup>
                <eMedDevice.WaveFormGraphicGroup>
                    <eMedDevice.41>E</eMedDevice.41>
                    <eMedDevice.42>NFJCelpPV25wU2NGTU96V1NScjB1d2JLTVFJOTI0Z25qWVNoTWNqVW9wWTAyYUF4T3A=</eMedDevice.42>
                </eMedDevice.WaveFormGraphicGroup>
                <eMedDevice.WaveFormGraphicGroup>
                    <eMedDevice.41>v</eMedDevice.41>
                    <eMedDevice.42>QjQ5UTFNaFhmcjAzUzBIVUhoSzBaaVZJNGJ5VXFRUzdFQnlDQVl4WkR2aDNpdWVXNzI=</eMedDevice.42>
                </eMedDevice.WaveFormGraphicGroup>
                <eMedDevice.WaveFormGraphicGroup>
                    <eMedDevice.41>I</eMedDevice.41>
                    <eMedDevice.42>WmRycmo5NFRiQVJ1QTV0WUF1eldHQTR6SUJ4eThqRXZCN2haRTh3WHVhZzFOYUVacVE=</eMedDevice.42>
                </eMedDevice.WaveFormGraphicGroup>
                <eMedDevice.WaveFormGraphicGroup>
                    <eMedDevice.41>t</eMedDevice.41>
                    <eMedDevice.42>MkVwbFcxY2dzclFwQ2hHcnlOV0FPbVdMZWpDNklHQXZsQnN6MlBITUNuaWFjS29mRFQ=</eMedDevice.42>
                </eMedDevice.WaveFormGraphicGroup>
            </eMedDevice.LabImageGroup>
            <eMedDevice.LabImageGroup>
                <eMedDevice.39>3405001</eMedDevice.39>
                <eMedDevice.40>1vE</eMedDevice.40>
                <eMedDevice.WaveFormGraphicGroup>
                    <eMedDevice.41>6</eMedDevice.41>
                    <eMedDevice.42>bmYzc1ZQcWdMSXdHTGJuRWVtM2ZZc1kxOHFpUm5FeGlTeUdRQXFucklTaDhXRE9oNlU=</eMedDevice.42>
                </eMedDevice.WaveFormGraphicGroup>
                <eMedDevice.WaveFormGraphicGroup>
                    <eMedDevice.41>4</eMedDevice.41>
                    <eMedDevice.42>TkxnWm02Qkk4Wk1kTGplbzhVMjVIUmlzb2Q4RXNtTkxQZ3VzZ2c4aEJ3Zm9QeDl1TGg=</eMedDevice.42>
                </eMedDevice.WaveFormGraphicGroup>
                <eMedDevice.WaveFormGraphicGroup>
                    <eMedDevice.41>a</eMedDevice.41>
                    <eMedDevice.42>cjBOMTRJdWVlc2ZOOWEyZ0FQTkpMcnZ3aUI1Q1p1ZTBqZ2VMRzRRd0tpQnNpdzJZYTQ=</eMedDevice.42>
                </eMedDevice.WaveFormGraphicGroup>
            </eMedDevice.LabImageGroup>
        </eMedDevice.LabsGroup>
        <eMedDevice.LabsGroup>
            <eMedDevice.36>2006-03-05T08:21:03+07:00</eMedDevice.36>
            <eMedDevice.LabResultGroup>
                <eMedDevice.37>3403045</eMedDevice.37>
                <eMedDevice.38>7</eMedDevice.38>
            </eMedDevice.LabResultGroup>
            <eMedDevice.LabResultGroup>
                <eMedDevice.37>3403045</eMedDevice.37>
                <eMedDevice.38>o</eMedDevice.38>
            </eMedDevice.LabResultGroup>
            <eMedDevice.LabImageGroup>
                <eMedDevice.39>3405001</eMedDevice.39>
                <eMedDevice.40>DdL</eMedDevice.40>
                <eMedDevice.WaveFormGraphicGroup>
                    <eMedDevice.41>d</eMedDevice.41>
                    <eMedDevice.42>YldwekFMc0g1dVgwUHNpSEFsRDNtT1lIZFI4R2xENHR4UG5hYXZIaE9zVWRQdWJMV08=</eMedDevice.42>
                </eMedDevice.WaveFormGraphicGroup>
                <eMedDevice.WaveFormGraphicGroup>
                    <eMedDevice.41>n</eMedDevice.41>
                    <eMedDevice.42>Rk5MemhmMWgwR01TWGgxSmEwRlJpOHhteVpqOERJTEdEQzY5UHBHOUgzSmQ2NFljb2M=</eMedDevice.42>
                </eMedDevice.WaveFormGraphicGroup>
                <eMedDevice.WaveFormGraphicGroup>
                    <eMedDevice.41>K</eMedDevice.41>
                    <eMedDevice.42>WHl3M2F2RkZtSTh3TVRlM29KWjZsMjE5VUY0VkpSOTh2bmV3N2tXd0Jqbmd4czFNSGI=</eMedDevice.42>
                </eMedDevice.WaveFormGraphicGroup>
                <eMedDevice.WaveFormGraphicGroup>
                    <eMedDevice.41>N</eMedDevice.41>
                    <eMedDevice.42>cjlmd2N5bVg1bHRsZXBVOXN0QlF3OEZJdm5QQlprNk1qMjB1bjM1WWJRdmdmUm80aGE=</eMedDevice.42>
                </eMedDevice.WaveFormGraphicGroup>
            </eMedDevice.LabImageGroup>
            <eMedDevice.LabImageGroup>
                <eMedDevice.39>3405001</eMedDevice.39>
                <eMedDevice.40>Dsw</eMedDevice.40>
                <eMedDevice.WaveFormGraphicGroup>
                    <eMedDevice.41>J</eMedDevice.41>
                    <eMedDevice.42>VzlBRUpXTGVyV0g3SGVsa25XT0hscmp3SnZWN3NkOFpnYjBZcTUwY3VuOE5qdFV6Q2I=</eMedDevice.42>
                </eMedDevice.WaveFormGraphicGroup>
                <eMedDevice.WaveFormGraphicGroup>
                    <eMedDevice.41>D</eMedDevice.41>
                    <eMedDevice.42>eW5NMGZPRzRHeGpYQ1kzZkRkQjc0MTYzYkJ4R2tpMG55R0JvaWxBR1JNc1dweWxwWjc=</eMedDevice.42>
                </eMedDevice.WaveFormGraphicGroup>
                <eMedDevice.WaveFormGraphicGroup>
                    <eMedDevice.41>I</eMedDevice.41>
                    <eMedDevice.42>bmd5OGw2YWxMV3FVUGkzRHdwd0p5cW9zdDZ5VXhiSXdXRTVVOUVrQ3lZTUVzQmFnYjc=</eMedDevice.42>
                </eMedDevice.WaveFormGraphicGroup>
                <eMedDevice.WaveFormGraphicGroup>
                    <eMedDevice.41>y</eMedDevice.41>
                    <eMedDevice.42>WDFYSDFOZXBQcnhnWDlBc2RPNGtIcnY5aUROaWR0SzBLT3VrNWZLNXE2NUxjb0Ztc1Q=</eMedDevice.42>
                </eMedDevice.WaveFormGraphicGroup>
            </eMedDevice.LabImageGroup>
            <eMedDevice.LabImageGroup>
                <eMedDevice.39>3405001</eMedDevice.39>
                <eMedDevice.40>FYu</eMedDevice.40>
                <eMedDevice.WaveFormGraphicGroup>
                    <eMedDevice.41>m</eMedDevice.41>
                    <eMedDevice.42>a2NjQ3FIeVF5OWhqTkhKTTQ2N2UwalFCTk1LWEJpTk1kZDBlc3g0bVNpUXllSUc5Sm8=</eMedDevice.42>
                </eMedDevice.WaveFormGraphicGroup>
                <eMedDevice.WaveFormGraphicGroup>
                    <eMedDevice.41>c</eMedDevice.41>
                    <eMedDevice.42>NkxoRmVJVzlpczY4SmoyRE5LeDl5ak4zVDZ3b0h1RkhXNkxNV3ZBUUg5SnJ0OTlEMDM=</eMedDevice.42>
                </eMedDevice.WaveFormGraphicGroup>
                <eMedDevice.WaveFormGraphicGroup>
                    <eMedDevice.41>K</eMedDevice.41>
                    <eMedDevice.42>ckROUm9KbHE2VHFLZkJNa0Y2VVNoZTlMWWtNWDNhQ2V5T3pqVVV0b1ExQTU4ZmpjRWo=</eMedDevice.42>
                </eMedDevice.WaveFormGraphicGroup>
                <eMedDevice.WaveFormGraphicGroup>
                    <eMedDevice.41>Z</eMedDevice.41>
                    <eMedDevice.42>YnpLcXFJejZ5YlJSNXAwQXNRSUZqY3V4WGhmRUM5NDJTMkhaakVKbVlLZEJ0TERsRjU=</eMedDevice.42>
                </eMedDevice.WaveFormGraphicGroup>
            </eMedDevice.LabImageGroup>
        </eMedDevice.LabsGroup>
        <eMedDevice.LabsGroup>
            <eMedDevice.36>1955-06-04T03:22:15+07:00</eMedDevice.36>
            <eMedDevice.LabResultGroup>
                <eMedDevice.37>3403045</eMedDevice.37>
                <eMedDevice.38>m</eMedDevice.38>
            </eMedDevice.LabResultGroup>
            <eMedDevice.LabResultGroup>
                <eMedDevice.37>3403045</eMedDevice.37>
                <eMedDevice.38>i</eMedDevice.38>
            </eMedDevice.LabResultGroup>
            <eMedDevice.LabImageGroup>
                <eMedDevice.39>3405001</eMedDevice.39>
                <eMedDevice.40>wwD</eMedDevice.40>
                <eMedDevice.WaveFormGraphicGroup>
                    <eMedDevice.41>a</eMedDevice.41>
                    <eMedDevice.42>Wm5iTExXejNWbk9HVExDWVV0akVlakI4NFFMbVhWS0VCYnFMUFcybXFWUnlJakNHREo=</eMedDevice.42>
                </eMedDevice.WaveFormGraphicGroup>
                <eMedDevice.WaveFormGraphicGroup>
                    <eMedDevice.41>m</eMedDevice.41>
                    <eMedDevice.42>RENCd0RqOW9MdEFtclN4Mm83TmFKSWtlQnRIWFg2NFZ2MGR1QzRYT1puQ1pmdnJqejk=</eMedDevice.42>
                </eMedDevice.WaveFormGraphicGroup>
                <eMedDevice.WaveFormGraphicGroup>
                    <eMedDevice.41>S</eMedDevice.41>
                    <eMedDevice.42>R3dwWWRqTUtVRjJZRWtDQXU2Z0RINGg4Snhtam4wclB4V1RDTW9Gb0djNnU2bXROQ0o=</eMedDevice.42>
                </eMedDevice.WaveFormGraphicGroup>
                <eMedDevice.WaveFormGraphicGroup>
                    <eMedDevice.41>g</eMedDevice.41>
                    <eMedDevice.42>RzRZMGthVkVoNDVYSjlUUFFxOHJNUGRFQXltWXBnZXZ0TEppdThrVWZaYUQ0b2YzZzc=</eMedDevice.42>
                </eMedDevice.WaveFormGraphicGroup>
            </eMedDevice.LabImageGroup>
            <eMedDevice.LabImageGroup>
                <eMedDevice.39>3405001</eMedDevice.39>
                <eMedDevice.40>2uU</eMedDevice.40>
                <eMedDevice.WaveFormGraphicGroup>
                    <eMedDevice.41>D</eMedDevice.41>
                    <eMedDevice.42>YkM0M1RXeUM1WXdJdVhwMzhnNEFZRlA3SHh5VklUQlh5RDVBTUlNUFpjY3p0WFhTUmY=</eMedDevice.42>
                </eMedDevice.WaveFormGraphicGroup>
                <eMedDevice.WaveFormGraphicGroup>
                    <eMedDevice.41>Q</eMedDevice.41>
                    <eMedDevice.42>cEZDeGRMdWdMTENNaERmS0ZYYzQzSXJGWXJBYVh0U2JMREpYNHhqTDRxOFBCSjBsNG0=</eMedDevice.42>
                </eMedDevice.WaveFormGraphicGroup>
            </eMedDevice.LabImageGroup>
            <eMedDevice.LabImageGroup>
                <eMedDevice.39>3405001</eMedDevice.39>
                <eMedDevice.40>pcl</eMedDevice.40>
                <eMedDevice.WaveFormGraphicGroup>
                    <eMedDevice.41>I</eMedDevice.41>
                    <eMedDevice.42>dDh0NkNaQm1uUDZpWTZzTmdEOE5obnQwTjIyNXZZa1RrSXJwd3dWQTFINTRyOXRCdFg=</eMedDevice.42>
                </eMedDevice.WaveFormGraphicGroup>
                <eMedDevice.WaveFormGraphicGroup>
                    <eMedDevice.41>1</eMedDevice.41>
                    <eMedDevice.42>YUlvU2dreUN4bERRZzJTM3pHME1ZT2g5cnJ4QW9NcVpvS3NNdHc2R1AzZU1ST1FJZ0g=</eMedDevice.42>
                </eMedDevice.WaveFormGraphicGroup>
                <eMedDevice.WaveFormGraphicGroup>
                    <eMedDevice.41>G</eMedDevice.41>
                    <eMedDevice.42>ekZOMXkxRFJkc0F2S1VkQnJsYnh2Wm9xcnprRnhrNXdocmNnT0tCellPMnh0aFlzMzY=</eMedDevice.42>
                </eMedDevice.WaveFormGraphicGroup>
                <eMedDevice.WaveFormGraphicGroup>
                    <eMedDevice.41>X</eMedDevice.41>
                    <eMedDevice.42>WlhxREI3aU0yZUt0YTBjT2EzZUJwN1ZUWFMxb1Q2QTlXQXJWcWJWWXZUZ0lTaTlsMGk=</eMedDevice.42>
                </eMedDevice.WaveFormGraphicGroup>
                <eMedDevice.WaveFormGraphicGroup>
                    <eMedDevice.41>Z</eMedDevice.41>
                    <eMedDevice.42>eklBdERGN2c3allnSFY5ZEZnSXJKSUlSeFpWTUNreTRiUDlydFBDNUZwSmpCdlhRcnY=</eMedDevice.42>
                </eMedDevice.WaveFormGraphicGroup>
            </eMedDevice.LabImageGroup>
        </eMedDevice.LabsGroup>
        <eMedDevice.DeviceGroup>
            <eMedDevice.43>6I</eMedDevice.43>
            <eMedDevice.44>1965-02-09T02:41:42+07:00</eMedDevice.44>
            <eMedDevice.45>4103043</eMedDevice.45>
            <eMedDevice.45>4103005</eMedDevice.45>
            <eMedDevice.45>4103041</eMedDevice.45>
            <eMedDevice.45>4103007</eMedDevice.45>
            <eMedDevice.WaveGroup>
                <eMedDevice.46>5</eMedDevice.46>
                <eMedDevice.47>UGJSY2h2RzdSUkU4UXNEVjkwTndEbHVVY3dLNVhMU2d4Q2puYzBRdEZ4d0drMHZvN2c=</eMedDevice.47>
                <eMedDevice.48>4106011</eMedDevice.48>
            </eMedDevice.WaveGroup>
            <eMedDevice.49>4107027</eMedDevice.49>
            <eMedDevice.49>4107017</eMedDevice.49>
            <eMedDevice.49>4107029</eMedDevice.49>
            <eMedDevice.50>A</eMedDevice.50>
            <eMedDevice.ShockGroup>
                <eMedDevice.51>4109001</eMedDevice.51>
                <eMedDevice.52>3980.0</eMedDevice.52>
                <eMedDevice.53>33</eMedDevice.53>
                <eMedDevice.54>164</eMedDevice.54>
            </eMedDevice.ShockGroup>
        </eMedDevice.DeviceGroup>
        <eMedDevice.DeviceGroup>
            <eMedDevice.43>ot</eMedDevice.43>
            <eMedDevice.44>2007-07-18T05:02:55+07:00</eMedDevice.44>
            <eMedDevice.45>4103043</eMedDevice.45>
            <eMedDevice.45>4103005</eMedDevice.45>
            <eMedDevice.45>4103041</eMedDevice.45>
            <eMedDevice.45>4103007</eMedDevice.45>
            <eMedDevice.45>4103001</eMedDevice.45>
            <eMedDevice.WaveGroup>
                <eMedDevice.46>U</eMedDevice.46>
                <eMedDevice.47>SXRPZ0k3NFZ3QTRUMDU5VmRPRHJJZ011SFlUZjZMWHYyWlNhRFFhQk96TVJBT1NCZnU=</eMedDevice.47>
                <eMedDevice.48>4106011</eMedDevice.48>
            </eMedDevice.WaveGroup>
            <eMedDevice.49>4107027</eMedDevice.49>
            <eMedDevice.49>4107017</eMedDevice.49>
            <eMedDevice.49>4107029</eMedDevice.49>
            <eMedDevice.49>4107015</eMedDevice.49>
            <eMedDevice.49>4107039</eMedDevice.49>
            <eMedDevice.50>T</eMedDevice.50>
            <eMedDevice.ShockGroup>
                <eMedDevice.51>4109001</eMedDevice.51>
                <eMedDevice.52>3763.0</eMedDevice.52>
                <eMedDevice.53>94</eMedDevice.53>
                <eMedDevice.54>644</eMedDevice.54>
            </eMedDevice.ShockGroup>
        </eMedDevice.DeviceGroup>
        <eMedDevice.DeviceGroup>
            <eMedDevice.43>yE</eMedDevice.43>
            <eMedDevice.44>1975-09-09T10:03:26+07:00</eMedDevice.44>
            <eMedDevice.45>4103043</eMedDevice.45>
            <eMedDevice.45>4103005</eMedDevice.45>
            <eMedDevice.45>4103041</eMedDevice.45>
            <eMedDevice.WaveGroup>
                <eMedDevice.46>3</eMedDevice.46>
                <eMedDevice.47>S013OFpMUEhnQlV4ZjRFOEw2REdmY0lib3AzMmk1Q2FWcHI2YWNYb1BnTkt4ZFpsd1Q=</eMedDevice.47>
                <eMedDevice.48>4106011</eMedDevice.48>
            </eMedDevice.WaveGroup>
            <eMedDevice.49>4107027</eMedDevice.49>
            <eMedDevice.49>4107017</eMedDevice.49>
            <eMedDevice.50>b</eMedDevice.50>
            <eMedDevice.ShockGroup>
                <eMedDevice.51>4109001</eMedDevice.51>
                <eMedDevice.52>1792.0</eMedDevice.52>
                <eMedDevice.53>86</eMedDevice.53>
                <eMedDevice.54>974</eMedDevice.54>
            </eMedDevice.ShockGroup>
        </eMedDevice.DeviceGroup>
        <eMedDevice.DeviceGroup>
            <eMedDevice.43>3y</eMedDevice.43>
            <eMedDevice.44>1988-09-24T04:40:38+07:00</eMedDevice.44>
            <eMedDevice.45>4103043</eMedDevice.45>
            <eMedDevice.45>4103005</eMedDevice.45>
            <eMedDevice.45>4103041</eMedDevice.45>
            <eMedDevice.WaveGroup>
                <eMedDevice.46>M</eMedDevice.46>
                <eMedDevice.47>a0g1eTlYVmg4OUlIRGhjWEplRnBuQTR2b1VsTnhrcmpuUFRnZGZDQlBMdWdsMVhLanU=</eMedDevice.47>
                <eMedDevice.48>4106011</eMedDevice.48>
            </eMedDevice.WaveGroup>
            <eMedDevice.49>4107027</eMedDevice.49>
            <eMedDevice.49>4107017</eMedDevice.49>
            <eMedDevice.50>A</eMedDevice.50>
            <eMedDevice.ShockGroup>
                <eMedDevice.51>4109001</eMedDevice.51>
                <eMedDevice.52>1488.0</eMedDevice.52>
                <eMedDevice.53>40</eMedDevice.53>
                <eMedDevice.54>258</eMedDevice.54>
            </eMedDevice.ShockGroup>
        </eMedDevice.DeviceGroup>
    </eMedDevice>
    <eCustomResults>
        <eCustomResults.ResultsGroup>
            <eCustomResults.01>Y</eCustomResults.01>
            <eCustomResults.01>J</eCustomResults.01>
            <eCustomResults.01>9</eCustomResults.01>
            <eCustomResults.01>l</eCustomResults.01>
            <eCustomResults.02>y</eCustomResults.02>
            <eCustomResults.03>8</eCustomResults.03>
        </eCustomResults.ResultsGroup>
        <eCustomResults.ResultsGroup>
            <eCustomResults.01>S</eCustomResults.01>
            <eCustomResults.01>Q</eCustomResults.01>
            <eCustomResults.01>o</eCustomResults.01>
            <eCustomResults.02>A</eCustomResults.02>
            <eCustomResults.03>i</eCustomResults.03>
        </eCustomResults.ResultsGroup>
        <eCustomResults.ResultsGroup>
            <eCustomResults.01>s</eCustomResults.01>
            <eCustomResults.01>H</eCustomResults.01>
            <eCustomResults.01>8</eCustomResults.01>
            <eCustomResults.01>q</eCustomResults.01>
            <eCustomResults.02>4</eCustomResults.02>
            <eCustomResults.03>X</eCustomResults.03>
        </eCustomResults.ResultsGroup>
    </eCustomResults>
</MedDeviceDataSet>
